{
  "TypeName": "Straw Hat",
  "MoneyValue": 100.0,
  "Description": "Keeps the sun off.",
  "Category": "Clothing",
  "Tags": [
    "Clothing"
  ],
  "FoodContent": 0.0,
  "DisplayName": "Straw Hat",
  "PlantToGenerate": "",
  "Tint": [
    255,
    255,
    255,
    255
  ],
  "AleName": "",

  "Tool_Breakable": false,
  "Tool_Durability": 4,
  "Tool_Wear": 0,
  "Tool_Effectiveness": 1.0,
  "Tool_AttackAnimation": "Attacking",
  "Tool_AttackTriggerFrame": 2,
  "Tool_AttackDamage": 1,
  "Tool_AttackHitEffect": "Effects\\hit",

  "Equipable": true,
  "Equipment_LayerType": "Hat",
  "Equipment_LayerName": "straw",
  "Equipment_Slot": "Hat",
  "Equipment_Palette": "Straw Equipment",

  "Gui_Graphic": {
    "AssetPath": "Entities/Dwarf/ToolIcons/equipment",
    "Palette": "Straw Equipment",
    "FrameSize": "32, 32",
    "Frame": "0, 6"
  },

  "Craft_Craftable": true,
  "Craft_Ingredients": [
    {
      "Tag": "Grain",
      "Count": 2
    }
  ],
  "Craft_ResultsCount": 1,
  "Craft_BaseCraftTime": 32.0,
  "Craft_Location": "Craft Table",
  "Craft_TaskCategory": "CraftItem",
  "Craft_Noise": "Craft",
  "Craft_MetaResourceFactory": "Normal"

}