{
  "TypeName": "Granite",
  "MaterialStrength": 50.0,
  "MoneyValue": 6.0,
  "Description": "A metamorphic rock, granite is produced when sandstones and shales are compressed deep under ground.",
  "Category": "Stone",
  "Tags": [
    "Stone",
    "Material",
    "HardMaterial",
    "Granite",
    "TrinketMaterial"
  ],
  "FoodContent": 0.0,
  "DisplayName": "Granite",
  "PlantToGenerate": null,
  "Tint": [
    255,
    255,
    255,
    255
  ],
  "AleName": "",

  "Gui_Graphic": {
    "AssetPath": "newgui/resources",
    "Palette": "None",
    "FrameSize": "32, 32",
    "Frame": "3, 6"
  },

  "Trinket_TrinketData": [
    {
      "Name": "Ring",
      "Value": 1.5,
      "Graphic": {
        "AssetPath": "newgui/trinkets-new",
        "Palette": "Stone Equipment",
        "FrameSize": "32, 32",
        "Frame": "0, 0"
      },
      "EncrustingGraphic": {
        "AssetPath": "newgui/trinkets-new",
        "Palette": "None",
        "FrameSize": "32, 32",
        "Frame": "0, 3"
      }
    },
    {
      "Name": "Bracer",
      "Value": 1.8,
      "Graphic": {
        "AssetPath": "newgui/trinkets-new",
        "Palette": "Stone Equipment",
        "FrameSize": "32, 32",
        "Frame": "1, 0"
      },
      "EncrustingGraphic": {
        "AssetPath": "newgui/trinkets-new",
        "Palette": "None",
        "FrameSize": "32, 32",
        "Frame": "1, 3"
      }
    },
    {
      "Name": "Pendant",
      "Value": 1.6,
      "Graphic": {
        "AssetPath": "newgui/trinkets-new",
        "Palette": "Stone Equipment",
        "FrameSize": "32, 32",
        "Frame": "2, 0"
      },
      "EncrustingGraphic": {
        "AssetPath": "newgui/trinkets-new",
        "Palette": "None",
        "FrameSize": "32, 32",
        "Frame": "2, 3"
      }
    },
    {
      "Name": "Figure",
      "Value": 3.0,
      "Graphic": {
        "AssetPath": "newgui/trinkets-new",
        "Palette": "Stone Equipment",
        "FrameSize": "32, 32",
        "Frame": "3, 0"
      },
      "EncrustingGraphic": {
        "AssetPath": "newgui/trinkets-new",
        "Palette": "None",
        "FrameSize": "32, 32",
        "Frame": "3, 3"
      }
    },
    {
      "Name": "Earrings",
      "Value": 2.0,
      "Graphic": {
        "AssetPath": "newgui/trinkets-new",
        "Palette": "Stone Equipment",
        "FrameSize": "32, 32",
        "Frame": "4, 0"
      },
      "EncrustingGraphic": {
        "AssetPath": "newgui/trinkets-new",
        "Palette": "None",
        "FrameSize": "32, 32",
        "Frame": "4, 3"
      }
    },
    {
      "Name": "Staff",
      "Value": 3.5,
      "Graphic": {
        "AssetPath": "newgui/trinkets-new",
        "Palette": "Stone Equipment",
        "FrameSize": "32, 32",
        "Frame": "5, 0"
      },
      "EncrustingGraphic": {
        "AssetPath": "newgui/trinkets-new",
        "Palette": "None",
        "FrameSize": "32, 32",
        "Frame": "5, 3"
      }
    },
    {
      "Name": "Crown",
      "Value": 4.0,
      "Graphic": {
        "AssetPath": "newgui/trinkets-new",
        "Palette": "Stone Equipment",
        "FrameSize": "32, 32",
        "Frame": "6, 0"
      },
      "EncrustingGraphic": {
        "AssetPath": "newgui/trinkets-new",
        "Palette": "None",
        "FrameSize": "32, 32",
        "Frame": "6, 3"
      }
    }
  ]
}