{
  "Name": "Punching Bag",
  "EntityName": "Punching Bag",
  "Category": "Furniture",
  "RequiredResources": [
    {
      "Tag": "Grain",
      "Count": 4
    }
  ],
  "Icon": {
    "Sheet": "furniture",
    "Tile": 42
  },
  "BaseCraftTime": 10.0,
  "Description": "Dwarves can train by hitting the Punching Bag.",
  "Type": "Object",
  "Prerequisites": [
    "OnGround"
  ],
  "ResourceCreated": "",
  "CraftLocation": "Craft Table",
  "Verb": "Build",
  "PastTeseVerb": "Built",
  "CurrentVerb": "Building",
  "AllowHeterogenous": false,
  "SpawnOffset": "0, 0.5, 0",
  "AddToOwnedPool": true,
  "CraftActBehavior": "Object",
  "Tutorial": "Dwarfs attack and destroy punching bags to gain XP and level up."
}